{
    "name": "Custom Field Suite",
    "slug": "custom-field-suite",
    "version": "2.6.5",
    "author": "Matt Gibbs",
    "author_profile": "https:\/\/profiles.wordpress.org\/mgibbs189\/",
    "contributors": {
        "mgibbs189": {
            "profile": "https:\/\/profiles.wordpress.org\/mgibbs189\/",
            "avatar": "https:\/\/secure.gravatar.com\/avatar\/a8cdaecd1b7a5ddae9bbf68b5b945d07?s=96&d=monsterid&r=g",
            "display_name": "Matt Gibbs"
        }
    },
    "requires": "5.0",
    "tested": "6.4.4",
    "requires_php": false,
    "requires_plugins": [],
    "compatibility": [],
    "rating": 96,
    "ratings": {
        "5": 132,
        "4": 5,
        "3": 0,
        "2": 1,
        "1": 5
    },
    "num_ratings": 143,
    "support_url": "https:\/\/wordpress.org\/support\/plugin\/custom-field-suite\/",
    "support_threads": 8,
    "support_threads_resolved": 1,
    "active_installs": 50000,
    "downloaded": 604073,
    "last_updated": "2024-02-27 7:11pm GMT",
    "added": "2011-10-01",
    "homepage": "",
    "sections": {
        "description": "<p>Custom Field Suite (CFS) lets you add custom fields to your posts. It&#8217;s lightweight and battle-tested (there&#8217;s not much to break).<\/p>\n<h4>Things to know<\/h4>\n<ul>\n<li>We do not provide support.<\/li>\n<li>This is a free plugin. We&#8217;re not selling anything.<\/li>\n<li>CFS includes 14 <a href=\"https:\/\/mgibbs189.github.io\/custom-field-suite\/field-types.html\" rel=\"nofollow ugc\">field types<\/a>. There are no plans to add more.<\/li>\n<li>If you want all the bells-and-whistles, use ACF.<\/li>\n<\/ul>\n<h4>Field types<\/h4>\n<ul>\n<li>Text<\/li>\n<li>Textarea<\/li>\n<li>WYSIWYG<\/li>\n<li>Date<\/li>\n<li>Color<\/li>\n<li>True \/ False<\/li>\n<li>Select<\/li>\n<li>File Upload<\/li>\n<li>Relationship<\/li>\n<li>Term<\/li>\n<li>User<\/li>\n<li>Loop (repeatable fields)<\/li>\n<li>Hyperlink<\/li>\n<li>Tab (group fields)<\/li>\n<\/ul>\n<h4>Usage<\/h4>\n<ul>\n<li>Browse to the &#8220;Field Groups&#8221; admin menu<\/li>\n<li>Create a Field Group containing one or more custom fields<\/li>\n<li>Choose where the Field Group should appear, using the Placement Rules box<\/li>\n<li>Use the <a href=\"https:\/\/mgibbs189.github.io\/custom-field-suite\/api\/get.html\" rel=\"nofollow ugc\">get<\/a> method in your template files to display custom fields<\/li>\n<\/ul>\n<h4>Links<\/h4>\n<ul>\n<li><a href=\"https:\/\/mgibbs189.github.io\/custom-field-suite\/\" rel=\"nofollow ugc\">Documentation \u2192<\/a><\/li>\n<li><a href=\"https:\/\/github.com\/mgibbs189\/custom-field-suite\" rel=\"nofollow ugc\">Github \u2192<\/a><\/li>\n<\/ul>\n",
        "changelog": "<h4>2.6.5<\/h4>\n<ul>\n<li>Extra sanitization to prevent XSS via admin-imported field groups (props WordFence)<\/li>\n<\/ul>\n<h4>2.6.4<\/h4>\n<ul>\n<li>Fixed: cleared PHP8 deprecation notices<\/li>\n<\/ul>\n<h4>2.6.3<\/h4>\n<ul>\n<li>Fixed: possible placement rules XSS (props Patchstack)<\/li>\n<\/ul>\n<h4>2.6.2.1<\/h4>\n<ul>\n<li>Confirmed 6.0.1 compatibility<\/li>\n<\/ul>\n<h4>2.6.2<\/h4>\n<ul>\n<li>Removed broken links, confirmed 5.9 compatibility<\/li>\n<\/ul>\n<h4>2.6.1<\/h4>\n<ul>\n<li>Fixed: PHP8 warnings<\/li>\n<\/ul>\n<h4>2.6<\/h4>\n<p>New: moved CFS into &#8220;Settings&#8221; menu<br \/>\nImproved: relationship fields now only run 1 query to retrieve related posts<br \/>\nImproved: code modernization<br \/>\nImproved: styling tweaks<br \/>\nFix: &#8220;Posts&#8221; field group rule ajax wasn&#8217;t loading<\/p>\n",
        "screenshots": "<ol><li><a href=\"https:\/\/ps.w.org\/custom-field-suite\/assets\/screenshot-1.png?rev=1853643\"><img src=\"https:\/\/ps.w.org\/custom-field-suite\/assets\/screenshot-1.png?rev=1853643\" alt=\"\"><\/a><\/li><li><a href=\"https:\/\/ps.w.org\/custom-field-suite\/assets\/screenshot-2.png?rev=1853643\"><img src=\"https:\/\/ps.w.org\/custom-field-suite\/assets\/screenshot-2.png?rev=1853643\" alt=\"\"><\/a><\/li><li><a href=\"https:\/\/ps.w.org\/custom-field-suite\/assets\/screenshot-3.png?rev=1853643\"><img src=\"https:\/\/ps.w.org\/custom-field-suite\/assets\/screenshot-3.png?rev=1853643\" alt=\"\"><\/a><\/li><li><a href=\"https:\/\/ps.w.org\/custom-field-suite\/assets\/screenshot-4.png?rev=1853643\"><img src=\"https:\/\/ps.w.org\/custom-field-suite\/assets\/screenshot-4.png?rev=1853643\" alt=\"\"><\/a><\/li><\/ol>",
        "reviews": "<div class=\"review\">\n\t<div class=\"review-head\">\n\t\t<div class=\"reviewer-info\">\n\t\t\t<div class=\"review-title-section\">\n\t\t\t\t<h4 class=\"review-title\">My best solution!<\/h4>\n\t\t\t\t<div class=\"star-rating\">\n\t\t\t\t<div class=\"wporg-ratings\" aria-label=\"5 out of 5 stars\" data-title-template=\"%s out of 5 stars\" data-rating=\"5\" style=\"color:#ffb900;\"><span class=\"star dashicons dashicons-star-filled\"><\/span><span class=\"star dashicons dashicons-star-filled\"><\/span><span class=\"star dashicons dashicons-star-filled\"><\/span><span class=\"star dashicons dashicons-star-filled\"><\/span><span class=\"star dashicons dashicons-star-filled\"><\/span><\/div>\t\t\t\t<\/div>\n\t\t\t<\/div>\n\t\t\t<p class=\"reviewer\">\n\t\t\t\tBy <a href=\"https:\/\/profiles.wordpress.org\/mellypetty\/\"><img alt='' src='https:\/\/secure.gravatar.com\/avatar\/4052669420dd32ac1e16875f3598b80a?s=16&#038;d=monsterid&#038;r=g' srcset='https:\/\/secure.gravatar.com\/avatar\/4052669420dd32ac1e16875f3598b80a?s=32&#038;d=monsterid&#038;r=g 2x' class='avatar avatar-16 photo' height='16' width='16' loading='lazy' decoding='async'\/><\/a><a href=\"https:\/\/profiles.wordpress.org\/mellypetty\/\" class=\"reviewer-name\">mellypetty<\/a> on <span class=\"review-date\">March 12, 2024<\/span>\t\t\t<\/p>\n\t\t<\/div>\n\t<\/div>\n\t<div class=\"review-body\"><!-- wp:paragraph -->\n<p class=\"\">I use this plugin frequently. Thank you for developing a helpful plugin. The easy-to-understand UI for non-developers has saved a lot of people.<br \/>I register my Contact Form 7 entries into Custom Field Suite and it is really useful.<br \/>When the number of items in the loop exceeds about 200, it seems that no more data can be saved, but there is no particular inconvenience.<\/p>\n<!-- \/wp:paragraph --><\/div>\n<\/div>\n<div class=\"review\">\n\t<div class=\"review-head\">\n\t\t<div class=\"reviewer-info\">\n\t\t\t<div class=\"review-title-section\">\n\t\t\t\t<h4 class=\"review-title\">Easy to use<\/h4>\n\t\t\t\t<div class=\"star-rating\">\n\t\t\t\t<div class=\"wporg-ratings\" aria-label=\"5 out of 5 stars\" data-title-template=\"%s out of 5 stars\" data-rating=\"5\" style=\"color:#ffb900;\"><span class=\"star dashicons dashicons-star-filled\"><\/span><span class=\"star dashicons dashicons-star-filled\"><\/span><span class=\"star dashicons dashicons-star-filled\"><\/span><span class=\"star dashicons dashicons-star-filled\"><\/span><span class=\"star dashicons dashicons-star-filled\"><\/span><\/div>\t\t\t\t<\/div>\n\t\t\t<\/div>\n\t\t\t<p class=\"reviewer\">\n\t\t\t\tBy <a href=\"https:\/\/profiles.wordpress.org\/jamaan\/\"><img alt='' src='https:\/\/secure.gravatar.com\/avatar\/e46a4d6139ac5bfb57c469a0169acd9e?s=16&#038;d=monsterid&#038;r=g' srcset='https:\/\/secure.gravatar.com\/avatar\/e46a4d6139ac5bfb57c469a0169acd9e?s=32&#038;d=monsterid&#038;r=g 2x' class='avatar avatar-16 photo' height='16' width='16' loading='lazy' decoding='async'\/><\/a><a href=\"https:\/\/profiles.wordpress.org\/jamaan\/\" class=\"reviewer-name\">jamaan<\/a> on <span class=\"review-date\">January 11, 2024<\/span>\t\t\t<\/p>\n\t\t<\/div>\n\t<\/div>\n\t<div class=\"review-body\"><!-- wp:paragraph -->\n<p class=\"\">We were looking for an alternative to ACF Pro since it incurs the cost for the clients and<\/p>\n<!-- \/wp:paragraph -->\n\n<!-- wp:quote -->\n<blockquote class=\"wp-block-quote\"><!-- wp:paragraph -->\n<p class=\"\">We found this gem of a plugin<\/p>\n<!-- \/wp:paragraph --><\/blockquote>\n<!-- \/wp:quote -->\n\n<!-- wp:paragraph -->\n<p class=\"\">and have been using it since then. Though it has limitations but still is very useful.<\/p>\n<!-- \/wp:paragraph -->\n\n<!-- wp:quote -->\n<blockquote class=\"wp-block-quote\"><!-- wp:paragraph -->\n<p class=\"\">9\/10 as a replacement to ACF Pro<\/p>\n<!-- \/wp:paragraph --><\/blockquote>\n<!-- \/wp:quote --><\/div>\n<\/div>\n<div class=\"review\">\n\t<div class=\"review-head\">\n\t\t<div class=\"reviewer-info\">\n\t\t\t<div class=\"review-title-section\">\n\t\t\t\t<h4 class=\"review-title\">It has everything you need.<\/h4>\n\t\t\t\t<div class=\"star-rating\">\n\t\t\t\t<div class=\"wporg-ratings\" aria-label=\"4 out of 5 stars\" data-title-template=\"%s out of 5 stars\" data-rating=\"4\" style=\"color:#ffb900;\"><span class=\"star dashicons dashicons-star-filled\"><\/span><span class=\"star dashicons dashicons-star-filled\"><\/span><span class=\"star dashicons dashicons-star-filled\"><\/span><span class=\"star dashicons dashicons-star-filled\"><\/span><span class=\"star dashicons dashicons-star-empty\"><\/span><\/div>\t\t\t\t<\/div>\n\t\t\t<\/div>\n\t\t\t<p class=\"reviewer\">\n\t\t\t\tBy <a href=\"https:\/\/profiles.wordpress.org\/aculine\/\"><img alt='' src='https:\/\/secure.gravatar.com\/avatar\/ae0996b4e18203e808fe0bbe856b9222?s=16&#038;d=monsterid&#038;r=g' srcset='https:\/\/secure.gravatar.com\/avatar\/ae0996b4e18203e808fe0bbe856b9222?s=32&#038;d=monsterid&#038;r=g 2x' class='avatar avatar-16 photo' height='16' width='16' loading='lazy' decoding='async'\/><\/a><a href=\"https:\/\/profiles.wordpress.org\/aculine\/\" class=\"reviewer-name\">aculine<\/a> on <span class=\"review-date\">November 29, 2023<\/span>\t\t\t<\/p>\n\t\t<\/div>\n\t<\/div>\n\t<div class=\"review-body\"><!-- wp:paragraph -->\n<p class=\"\">Simple and functional. It has everything you need.<\/p>\n<!-- \/wp:paragraph --><\/div>\n<\/div>\n<div class=\"review\">\n\t<div class=\"review-head\">\n\t\t<div class=\"reviewer-info\">\n\t\t\t<div class=\"review-title-section\">\n\t\t\t\t<h4 class=\"review-title\">Quick and Easy<\/h4>\n\t\t\t\t<div class=\"star-rating\">\n\t\t\t\t<div class=\"wporg-ratings\" aria-label=\"5 out of 5 stars\" data-title-template=\"%s out of 5 stars\" data-rating=\"5\" style=\"color:#ffb900;\"><span class=\"star dashicons dashicons-star-filled\"><\/span><span class=\"star dashicons dashicons-star-filled\"><\/span><span class=\"star dashicons dashicons-star-filled\"><\/span><span class=\"star dashicons dashicons-star-filled\"><\/span><span class=\"star dashicons dashicons-star-filled\"><\/span><\/div>\t\t\t\t<\/div>\n\t\t\t<\/div>\n\t\t\t<p class=\"reviewer\">\n\t\t\t\tBy <a href=\"https:\/\/profiles.wordpress.org\/mcaravaglia\/\"><img alt='' src='https:\/\/secure.gravatar.com\/avatar\/ac367f59f1440778b542e1f8890392a0?s=16&#038;d=monsterid&#038;r=g' srcset='https:\/\/secure.gravatar.com\/avatar\/ac367f59f1440778b542e1f8890392a0?s=32&#038;d=monsterid&#038;r=g 2x' class='avatar avatar-16 photo' height='16' width='16' loading='lazy' decoding='async'\/><\/a><a href=\"https:\/\/profiles.wordpress.org\/mcaravaglia\/\" class=\"reviewer-name\">mcaravaglia<\/a> on <span class=\"review-date\">June 17, 2023<\/span>\t\t\t<\/p>\n\t\t<\/div>\n\t<\/div>\n\t<div class=\"review-body\"><!-- wp:paragraph -->\n<p>Did exactly what I needed it to do; quickly and easily<\/p>\n<!-- \/wp:paragraph --><\/div>\n<\/div>\n<div class=\"review\">\n\t<div class=\"review-head\">\n\t\t<div class=\"reviewer-info\">\n\t\t\t<div class=\"review-title-section\">\n\t\t\t\t<h4 class=\"review-title\">Better than ACF ^^<\/h4>\n\t\t\t\t<div class=\"star-rating\">\n\t\t\t\t<div class=\"wporg-ratings\" aria-label=\"5 out of 5 stars\" data-title-template=\"%s out of 5 stars\" data-rating=\"5\" style=\"color:#ffb900;\"><span class=\"star dashicons dashicons-star-filled\"><\/span><span class=\"star dashicons dashicons-star-filled\"><\/span><span class=\"star dashicons dashicons-star-filled\"><\/span><span class=\"star dashicons dashicons-star-filled\"><\/span><span class=\"star dashicons dashicons-star-filled\"><\/span><\/div>\t\t\t\t<\/div>\n\t\t\t<\/div>\n\t\t\t<p class=\"reviewer\">\n\t\t\t\tBy <a href=\"https:\/\/profiles.wordpress.org\/stwwndrr\/\"><img alt='' src='https:\/\/secure.gravatar.com\/avatar\/26f0f12f034f036fc123734120a3ed1e?s=16&#038;d=monsterid&#038;r=g' srcset='https:\/\/secure.gravatar.com\/avatar\/26f0f12f034f036fc123734120a3ed1e?s=32&#038;d=monsterid&#038;r=g 2x' class='avatar avatar-16 photo' height='16' width='16' loading='lazy' decoding='async'\/><\/a><a href=\"https:\/\/profiles.wordpress.org\/stwwndrr\/\" class=\"reviewer-name\">stwwndrr<\/a> on <span class=\"review-date\">May 26, 2023<\/span>\t\t\t<\/p>\n\t\t<\/div>\n\t<\/div>\n\t<div class=\"review-body\"><!-- wp:paragraph -->\n<p>The plugin is worthy of attention, it copes with certain tasks better than ACF<\/p>\n<!-- \/wp:paragraph --><\/div>\n<\/div>\n<div class=\"review\">\n\t<div class=\"review-head\">\n\t\t<div class=\"reviewer-info\">\n\t\t\t<div class=\"review-title-section\">\n\t\t\t\t<h4 class=\"review-title\">Simple, powerful and functional<\/h4>\n\t\t\t\t<div class=\"star-rating\">\n\t\t\t\t<div class=\"wporg-ratings\" aria-label=\"5 out of 5 stars\" data-title-template=\"%s out of 5 stars\" data-rating=\"5\" style=\"color:#ffb900;\"><span class=\"star dashicons dashicons-star-filled\"><\/span><span class=\"star dashicons dashicons-star-filled\"><\/span><span class=\"star dashicons dashicons-star-filled\"><\/span><span class=\"star dashicons dashicons-star-filled\"><\/span><span class=\"star dashicons dashicons-star-filled\"><\/span><\/div>\t\t\t\t<\/div>\n\t\t\t<\/div>\n\t\t\t<p class=\"reviewer\">\n\t\t\t\tBy <a href=\"https:\/\/profiles.wordpress.org\/diegosomar\/\"><img alt='' src='https:\/\/secure.gravatar.com\/avatar\/9bde1caac4ba17c496ef35bc2cc279b0?s=16&#038;d=monsterid&#038;r=g' srcset='https:\/\/secure.gravatar.com\/avatar\/9bde1caac4ba17c496ef35bc2cc279b0?s=32&#038;d=monsterid&#038;r=g 2x' class='avatar avatar-16 photo' height='16' width='16' loading='lazy' decoding='async'\/><\/a><a href=\"https:\/\/profiles.wordpress.org\/diegosomar\/\" class=\"reviewer-name\">diegosomar<\/a> on <span class=\"review-date\">March 30, 2023<\/span>\t\t\t<\/p>\n\t\t<\/div>\n\t<\/div>\n\t<div class=\"review-body\"><!-- wp:paragraph -->\n<p>At the same time that it is simple, it is very powerful and helps a lot in development, especially with the field repeater.<\/p>\n<!-- \/wp:paragraph -->\n\n<!-- wp:paragraph -->\n<p>Thanks to the developer.<\/p>\n<!-- \/wp:paragraph --><\/div>\n<\/div>\n<div class=\"review\">\n\t<div class=\"review-head\">\n\t\t<div class=\"reviewer-info\">\n\t\t\t<div class=\"review-title-section\">\n\t\t\t\t<h4 class=\"review-title\">\u041d\u0435 \u0440\u0430\u0431\u043e\u0442\u0430\u0435\u0442<\/h4>\n\t\t\t\t<div class=\"star-rating\">\n\t\t\t\t<div class=\"wporg-ratings\" aria-label=\"1 out of 5 stars\" data-title-template=\"%s out of 5 stars\" data-rating=\"1\" style=\"color:#ffb900;\"><span class=\"star dashicons dashicons-star-filled\"><\/span><span class=\"star dashicons dashicons-star-empty\"><\/span><span class=\"star dashicons dashicons-star-empty\"><\/span><span class=\"star dashicons dashicons-star-empty\"><\/span><span class=\"star dashicons dashicons-star-empty\"><\/span><\/div>\t\t\t\t<\/div>\n\t\t\t<\/div>\n\t\t\t<p class=\"reviewer\">\n\t\t\t\tBy <a href=\"https:\/\/profiles.wordpress.org\/web39\/\"><img alt='' src='https:\/\/secure.gravatar.com\/avatar\/85c988776f49d5ac8d1eb91f707ca095?s=16&#038;d=monsterid&#038;r=g' srcset='https:\/\/secure.gravatar.com\/avatar\/85c988776f49d5ac8d1eb91f707ca095?s=32&#038;d=monsterid&#038;r=g 2x' class='avatar avatar-16 photo' height='16' width='16' loading='lazy' decoding='async'\/><\/a><a href=\"https:\/\/profiles.wordpress.org\/web39\/\" class=\"reviewer-name\">Roman Moiseenko <small>(web39)<\/small><\/a> on <span class=\"review-date\">October 6, 2022<\/span>\t\t\t<\/p>\n\t\t<\/div>\n\t<\/div>\n\t<div class=\"review-body\">CFS()-&gt;get() - \u043d\u0435 \u0440\u0430\u0431\u043e\u0442\u0430\u0435\u0442, \u0432\u043e\u0437\u0432\u0440\u0430\u0449\u0430\u0435\u0442 \u043f\u0443\u0441\u0442\u043e\u0439 \u043c\u0430\u0441\u0441\u0438\u0432, CFS()-&gt;get() === array()\n\u043f\u043e Id \u0440\u0430\u0431\u043e\u0442\u0430\u0435\u0442<\/div>\n<\/div>\n<div class=\"review\">\n\t<div class=\"review-head\">\n\t\t<div class=\"reviewer-info\">\n\t\t\t<div class=\"review-title-section\">\n\t\t\t\t<h4 class=\"review-title\">how to allow, limitation of extended fields in the cfs_field class<\/h4>\n\t\t\t\t<div class=\"star-rating\">\n\t\t\t\t<div class=\"wporg-ratings\" aria-label=\"5 out of 5 stars\" data-title-template=\"%s out of 5 stars\" data-rating=\"5\" style=\"color:#ffb900;\"><span class=\"star dashicons dashicons-star-filled\"><\/span><span class=\"star dashicons dashicons-star-filled\"><\/span><span class=\"star dashicons dashicons-star-filled\"><\/span><span class=\"star dashicons dashicons-star-filled\"><\/span><span class=\"star dashicons dashicons-star-filled\"><\/span><\/div>\t\t\t\t<\/div>\n\t\t\t<\/div>\n\t\t\t<p class=\"reviewer\">\n\t\t\t\tBy <a href=\"https:\/\/profiles.wordpress.org\/jeanlarrota32\/\"><img alt='' src='https:\/\/secure.gravatar.com\/avatar\/db7415626e5c77583da64b37c7fb5a15?s=16&#038;d=monsterid&#038;r=g' srcset='https:\/\/secure.gravatar.com\/avatar\/db7415626e5c77583da64b37c7fb5a15?s=32&#038;d=monsterid&#038;r=g 2x' class='avatar avatar-16 photo' height='16' width='16' loading='lazy' decoding='async'\/><\/a><a href=\"https:\/\/profiles.wordpress.org\/jeanlarrota32\/\" class=\"reviewer-name\">jeanlarrota32<\/a> on <span class=\"review-date\">September 27, 2022<\/span>\t\t\t<\/p>\n\t\t<\/div>\n\t<\/div>\n\t<div class=\"review-body\">Hello, greetings.\n\nCongratulations for the plugin, despite its simplicity, it fulfills to add custom things to wordpress.\n\nI am adding a custom field similar to the user field, extending the cfs_field class.\n\nThe only problem I saw is that when I add the limitations, it doesn't take them in the backend.\n\nfrom what I saw in the code, it is because there is no filter that allows other fields to be accepted, that is what I see so far.\n\nthe code to which I refer is in\n\nplugins\\custom-field-suite\\includes\\form.php\n\nline 344\n\nwhere I have to add a filter as follows\n\n<pre><code>php\n$typesValidation = apply_filters(&#039;cfs_form_types_validation&#039;, [ &#039;relationship&#039;, &#039;user&#039;, &#039;loop&#039; ]);\n\nif ( in_array( $field-&gt;type, $typesValidation ) ) {<\/code><\/pre>\n\n\nI still can't find another way to do this without modifying the plugin code<\/div>\n<\/div>\n<div class=\"review\">\n\t<div class=\"review-head\">\n\t\t<div class=\"reviewer-info\">\n\t\t\t<div class=\"review-title-section\">\n\t\t\t\t<h4 class=\"review-title\">Best option for me!<\/h4>\n\t\t\t\t<div class=\"star-rating\">\n\t\t\t\t<div class=\"wporg-ratings\" aria-label=\"5 out of 5 stars\" data-title-template=\"%s out of 5 stars\" data-rating=\"5\" style=\"color:#ffb900;\"><span class=\"star dashicons dashicons-star-filled\"><\/span><span class=\"star dashicons dashicons-star-filled\"><\/span><span class=\"star dashicons dashicons-star-filled\"><\/span><span class=\"star dashicons dashicons-star-filled\"><\/span><span class=\"star dashicons dashicons-star-filled\"><\/span><\/div>\t\t\t\t<\/div>\n\t\t\t<\/div>\n\t\t\t<p class=\"reviewer\">\n\t\t\t\tBy <a href=\"https:\/\/profiles.wordpress.org\/dwqueretaro\/\"><img alt='' src='https:\/\/secure.gravatar.com\/avatar\/313304a705360ffa375046750e770ead?s=16&#038;d=monsterid&#038;r=g' srcset='https:\/\/secure.gravatar.com\/avatar\/313304a705360ffa375046750e770ead?s=32&#038;d=monsterid&#038;r=g 2x' class='avatar avatar-16 photo' height='16' width='16' loading='lazy' decoding='async'\/><\/a><a href=\"https:\/\/profiles.wordpress.org\/dwqueretaro\/\" class=\"reviewer-name\">Tokatl <small>(dwqueretaro)<\/small><\/a> on <span class=\"review-date\">September 21, 2022<\/span>\t\t\t<\/p>\n\t\t<\/div>\n\t<\/div>\n\t<div class=\"review-body\">Searching, testing that and that other but always the features I needed in other plugins were premium... then I found this fantastic plugin, clean, lite, no premium adds, completely free and has everything I need it like repeatable group of fields! Thanks to the developer for this! <\/div>\n<\/div>\n<div class=\"review\">\n\t<div class=\"review-head\">\n\t\t<div class=\"reviewer-info\">\n\t\t\t<div class=\"review-title-section\">\n\t\t\t\t<h4 class=\"review-title\">Almost<\/h4>\n\t\t\t\t<div class=\"star-rating\">\n\t\t\t\t<div class=\"wporg-ratings\" aria-label=\"4 out of 5 stars\" data-title-template=\"%s out of 5 stars\" data-rating=\"4\" style=\"color:#ffb900;\"><span class=\"star dashicons dashicons-star-filled\"><\/span><span class=\"star dashicons dashicons-star-filled\"><\/span><span class=\"star dashicons dashicons-star-filled\"><\/span><span class=\"star dashicons dashicons-star-filled\"><\/span><span class=\"star dashicons dashicons-star-empty\"><\/span><\/div>\t\t\t\t<\/div>\n\t\t\t<\/div>\n\t\t\t<p class=\"reviewer\">\n\t\t\t\tBy <a href=\"https:\/\/profiles.wordpress.org\/heavylogic\/\"><img alt='' src='https:\/\/secure.gravatar.com\/avatar\/47c1c1b69a4b4df52cb453fef36f275e?s=16&#038;d=monsterid&#038;r=g' srcset='https:\/\/secure.gravatar.com\/avatar\/47c1c1b69a4b4df52cb453fef36f275e?s=32&#038;d=monsterid&#038;r=g 2x' class='avatar avatar-16 photo' height='16' width='16' loading='lazy' decoding='async'\/><\/a><a href=\"https:\/\/profiles.wordpress.org\/heavylogic\/\" class=\"reviewer-name\">heavylogic<\/a> on <span class=\"review-date\">May 7, 2022<\/span>\t\t\t<\/p>\n\t\t<\/div>\n\t<\/div>\n\t<div class=\"review-body\">It can do almost everything I need. The only thing is - you can upload a file, but you can't pick already uploaded file from a library.<\/div>\n<\/div>\n"
    },
    "short_description": "Add custom fields to your post types",
    "description": "<p>Custom Field Suite (CFS) lets you add custom fields to your posts. It&#8217;s lightweight and battle-tested (there&#8217;s not much to break).<\/p>\n<h4>Things to know<\/h4>\n<ul>\n<li>We do not provide support.<\/li>\n<li>This is a free plugin. We&#8217;re not selling anything.<\/li>\n<li>CFS includes 14 <a href=\"https:\/\/mgibbs189.github.io\/custom-field-suite\/field-types.html\" rel=\"nofollow ugc\">field types<\/a>. There are no plans to add more.<\/li>\n<li>If you want all the bells-and-whistles, use ACF.<\/li>\n<\/ul>\n<h4>Field types<\/h4>\n<ul>\n<li>Text<\/li>\n<li>Textarea<\/li>\n<li>WYSIWYG<\/li>\n<li>Date<\/li>\n<li>Color<\/li>\n<li>True \/ False<\/li>\n<li>Select<\/li>\n<li>File Upload<\/li>\n<li>Relationship<\/li>\n<li>Term<\/li>\n<li>User<\/li>\n<li>Loop (repeatable fields)<\/li>\n<li>Hyperlink<\/li>\n<li>Tab (group fields)<\/li>\n<\/ul>\n<h4>Usage<\/h4>\n<ul>\n<li>Browse to the &#8220;Field Groups&#8221; admin menu<\/li>\n<li>Create a Field Group containing one or more custom fields<\/li>\n<li>Choose where the Field Group should appear, using the Placement Rules box<\/li>\n<li>Use the <a href=\"https:\/\/mgibbs189.github.io\/custom-field-suite\/api\/get.html\" rel=\"nofollow ugc\">get<\/a> method in your template files to display custom fields<\/li>\n<\/ul>\n<h4>Links<\/h4>\n<ul>\n<li><a href=\"https:\/\/mgibbs189.github.io\/custom-field-suite\/\" rel=\"nofollow ugc\">Documentation \u2192<\/a><\/li>\n<li><a href=\"https:\/\/github.com\/mgibbs189\/custom-field-suite\" rel=\"nofollow ugc\">Github \u2192<\/a><\/li>\n<\/ul>\n",
    "download_link": "https:\/\/downloads.wordpress.org\/plugin\/custom-field-suite.zip",
    "upgrade_notice": [],
    "screenshots": {
        "1": {
            "src": "https:\/\/ps.w.org\/custom-field-suite\/assets\/screenshot-1.png?rev=1853643",
            "caption": ""
        },
        "2": {
            "src": "https:\/\/ps.w.org\/custom-field-suite\/assets\/screenshot-2.png?rev=1853643",
            "caption": ""
        },
        "3": {
            "src": "https:\/\/ps.w.org\/custom-field-suite\/assets\/screenshot-3.png?rev=1853643",
            "caption": ""
        },
        "4": {
            "src": "https:\/\/ps.w.org\/custom-field-suite\/assets\/screenshot-4.png?rev=1853643",
            "caption": ""
        }
    },
    "tags": {
        "custom-fields": "custom fields",
        "fields": "fields",
        "postmeta": "postmeta",
        "relationship": "relationship",
        "repeater": "repeater"
    },
    "stable_tag": "trunk",
    "versions": [],
    "business_model": false,
    "repository_url": "",
    "commercial_support_url": "",
    "donate_link": "",
    "banners": [],
    "icons": {
        "1x": "https:\/\/ps.w.org\/custom-field-suite\/assets\/icon-128x128.png?rev=1112866",
        "2x": "https:\/\/ps.w.org\/custom-field-suite\/assets\/icon-256x256.png?rev=1112866"
    },
    "blocks": [],
    "block_assets": [],
    "author_block_count": 0,
    "author_block_rating": 96,
    "blueprints": [],
    "preview_link": "",
    "language_packs": [
        {
            "type": "plugin",
            "slug": "custom-field-suite",
            "language": "fa_IR",
            "version": "2.6.5",
            "updated": "2020-10-02 15:47:41",
            "package": "https:\/\/downloads.wordpress.org\/translation\/plugin\/custom-field-suite\/2.6.5\/fa_IR.zip"
        },
        {
            "type": "plugin",
            "slug": "custom-field-suite",
            "language": "ja",
            "version": "2.6.5",
            "updated": "2023-03-03 14:29:47",
            "package": "https:\/\/downloads.wordpress.org\/translation\/plugin\/custom-field-suite\/2.6.5\/ja.zip"
        },
        {
            "type": "plugin",
            "slug": "custom-field-suite",
            "language": "nb_NO",
            "version": "2.6.5",
            "updated": "2023-10-11 08:22:05",
            "package": "https:\/\/downloads.wordpress.org\/translation\/plugin\/custom-field-suite\/2.6.5\/nb_NO.zip"
        },
        {
            "type": "plugin",
            "slug": "custom-field-suite",
            "language": "ru_RU",
            "version": "2.6.5",
            "updated": "2023-06-19 19:28:11",
            "package": "https:\/\/downloads.wordpress.org\/translation\/plugin\/custom-field-suite\/2.6.5\/ru_RU.zip"
        }
    ]
}